server_setup.py
packets/__init__.py
packets/server.py
packets/common/__init__.py
packets/common/decos.py
packets/common/descriptors.py
packets/common/errors.py
packets/common/host_ping.py
packets/common/metaclass.py
packets/common/utils.py
packets/common/variables.py
packets/logs/__init__.py
packets/logs/config_client_log.py
packets/logs/config_server_log.py
packets/server/__init__.py
packets/server/add_user.py
packets/server/config_window.py
packets/server/core.py
packets/server/database.py
packets/server/history_windows.py
packets/server/main_window.py
packets/server/remove_user.py
packets/server/stat_window.py
packets/unit_tests/__init__.py
packets/unit_tests/decos.py
packets/unit_tests/test_client.py
packets/unit_tests/test_utils.py
ship_messenger_server.egg-info/PKG-INFO
ship_messenger_server.egg-info/SOURCES.txt
ship_messenger_server.egg-info/dependency_links.txt
ship_messenger_server.egg-info/requires.txt
ship_messenger_server.egg-info/top_level.txt