Metadata-Version: 1.0
Name: ship-messenger-server
Version: 0.8.7
Summary: ship messenger server
Home-page: UNKNOWN
Author: Vladimir Ruzhelovich
Author-email: Ruzhelovich.Vladimir@gmail.com
License: UNKNOWN
Platform: UNKNOWN
